my_own_package/__init__.py
robi_proiect_hello-0.2.0.dist-info/METADATA
robi_proiect_hello-0.2.0.dist-info/WHEEL
robi_proiect_hello-0.2.0.dist-info/top_level.txt
robi_proiect_hello-0.2.0.dist-info/RECORD
