Metadata-Version: 2.1
Name: robi-proiect-hello
Version: 0.2.0
Summary: Hello,Users!
Home-page: UNKNOWN
Author: Robert Preunca
Author-email: preunca.robert@gmail.com
License: UNKNOWN
Platform: UNKNOWN
